jinja2_base64_filters/__init__.py
jinja2_base64_filters/jinja2_base64_filters.py
jinja2_base64_filters-0.1.4.dist-info/LICENSE
jinja2_base64_filters-0.1.4.dist-info/METADATA
jinja2_base64_filters-0.1.4.dist-info/WHEEL
jinja2_base64_filters-0.1.4.dist-info/top_level.txt
jinja2_base64_filters-0.1.4.dist-info/RECORD
