Metadata-Version: 2.1
Name: jinja2-base64-filters
Version: 0.1.4
Summary: Tiny jinja2 extension to add b64encode and b64decode filters.
Home-page: https://github.com/lumapps/jinja2_base64_filters
Author: Timothée GERMAIN
Author-email: timothee@lumapps.com
License: MIT
Keywords: jinja2_base64_filters
Platform: UNKNOWN
Classifier: Development Status :: 2 - Pre-Alpha
Classifier: License :: OSI Approved :: MIT License
Classifier: Programming Language :: Python
Classifier: Programming Language :: Python :: 2
Classifier: Programming Language :: Python :: 2.7
Classifier: Programming Language :: Python :: 3
Classifier: Programming Language :: Python :: 3.7
Requires-Dist: jinja2
